README.md
setup.py
goes_solar_retriever.egg-info/PKG-INFO
goes_solar_retriever.egg-info/SOURCES.txt
goes_solar_retriever.egg-info/dependency_links.txt
goes_solar_retriever.egg-info/requires.txt
goes_solar_retriever.egg-info/top_level.txt
goessolarretriever/__init__.py
goessolarretriever/fetch.py
goessolarretriever/kinds.py
tests/test_fetch.py