Metadata-Version: 2.1
Name: goes_solar_retriever
Version: 0.5
Summary: Package to retrieve GOES solar data
Home-page: 
Author: Marcus Hughes
Author-email: hughes.jmb@gmail.com
Requires-Dist: pandas
Requires-Dist: bs4
Requires-Dist: tqdm
